{
    "key": "group_5fe4a2cc12709",
    "title": "Module - Snippet",
    "fields": [
        {
            "key": "field_5fe4a2da90256",
            "label": "Snippet",
            "name": "snippet",
            "type": "post_object",
            "instructions": "",
            "required": 0,
            "conditional_logic": 0,
            "wrapper": {
                "width": "",
                "class": "",
                "id": ""
            },
            "post_type": [
                "snippet"
            ],
            "taxonomy": "",
            "allow_null": 0,
            "multiple": 0,
            "return_format": "object",
            "ui": 1
        }
    ],
    "location": [
        [
            {
                "param": "post_type",
                "operator": "==",
                "value": "post"
            }
        ]
    ],
    "menu_order": 0,
    "position": "normal",
    "style": "default",
    "label_placement": "top",
    "instruction_placement": "label",
    "hide_on_screen": "",
    "active": false,
    "description": "",
    "modified": 1608819466
}